Workbook
Name company.name: Parms!$A$1
Name D.F.Interest.Expense: DebtSchedule!$K$18:$O$18
Name D.F.LTDebt: DebtSchedule!$K$22:$O$22
Name D.F.Revolver: DebtSchedule!$K$7:$O$7
Name D.F.STDebt: DebtSchedule!$K$21:$O$21
Name D.F.Sub.Debt: DebtSchedule!$K$8:$O$8
Name D.H.Interest.Expense: DebtSchedule!$G$18:$I$18
Name D.H.LTDebt: DebtSchedule!$G$22:$I$22
Name D.H.STDebt: DebtSchedule!$G$21:$I$21
Name D.Rate.Revolver: DebtSchedule!$K$15:$O$15
Name D.Rate.Sub.Debt: DebtSchedule!$K$16:$O$16
Name dates.forecast: Parms!$J$1:$N$1
Name dates.hist: Parms!$G$1:$I$1
Name DCF.Cash: 'Financial Statements'!$I$46
Name DCF.Debt: DebtSchedule!$I$9
Name DCF.Discount.Cash.Flow: 'DCF Analysis'!$G$26:$K$26
Name DCF.Equity: 'Financial Statements'!$I$82
Name DCF.Interest.Expense: DebtSchedule!$I$18
Name DCF.NPV.DCF: 'DCF Analysis'!$G$28
Name DCF.Pref.Stock: 'Financial Statements'!$I$78
Name DCF.Terminal.Discount.Factor: 'DCF Analysis'!$K$25
Name DCF.Terminal.EBITDA: 'DCF Analysis'!$K$15
Name DCF.Terminal.Free.Cash.Flow: 'DCF Analysis'!$K$24
Name DCF.Undiscounted.Cash.Flow: 'DCF Analysis'!$G$24:$K$24
Name EBITDA.LBO: 'Transaction Summary'!$G$3
Name F.Capital: 'Financial Statements'!$K$84:$O$84
Name F.Cash: 'Financial Statements'!$K$117:$O$117
Name F.Cash.Financing: 'Financial Statements'!$K$113:$O$113
Name F.Cash.Investment: 'Financial Statements'!$K$106:$O$106
Name F.Cash.Ops: 'Financial Statements'!$K$101:$O$101
Name F.COGS: 'Financial Statements'!$K$13:$O$13
Name F.EBIT: 'Financial Statements'!$K$28:$O$28
Name F.EBT: 'Financial Statements'!$K$33:$O$33
Name F.Equity: 'Financial Statements'!$K$82:$O$82
Name F.Fixed.Costs: 'Financial Statements'!$K$26:$O$26
Name F.Gross.Margin: 'Financial Statements'!$K$15:$O$15
Name F.Net.Income: 'Financial Statements'!$K$37:$O$37
Name F.Revenues: 'Financial Statements'!$K$7:$O$7
Name F.STarting.Cash: 'Financial Statements'!$K$116:$O$116
Name F.Total.Assets: 'Financial Statements'!$K$60:$O$60
Name FCF.Labels: 'DCF Analysis'!$C$15:$F$24
Name FCF.Values: 'DCF Analysis'!$G$15:$K$24
Name Final.Amortization.Expense: 'Financial Statements'!$I$25
Name Final.Depreciation.Expense: 'Financial Statements'!$I$24
Name Final.EBIT: 'Financial Statements'!$I$28
Name goldman.sachs.fee: 'Transaction Summary'!$G$19
Name H.Capital: 'Financial Statements'!$G$84:$I$84
Name H.Cash: 'Financial Statements'!$G$117:$I$117
Name H.Cash.Financing: 'Financial Statements'!$H$113:$I$113
Name H.Cash.From.Ops: 'Financial Statements'!$H$101:$I$101
Name H.Cash.Investment: 'Financial Statements'!$H$106:$I$106
Name H.COGS: 'Financial Statements'!$G$13:$I$13
Name H.EBIT: 'Financial Statements'!$G$28:$I$28
Name H.Fixed.Costs: 'Financial Statements'!$G$26:$I$26
Name H.Gross.Margin: 'Financial Statements'!$G$15:$I$15
Name H.Net.Income: 'Financial Statements'!$G$37:$I$37
Name H.Operating.Income: 'Financial Statements'!$G$28:$I$28
Name H.Revenues: 'Financial Statements'!$G$7:$I$7
Name H.Total.Assets: 'Financial Statements'!$G$60:$I$60
Name JPM.Fee: 'Transaction Summary'!$R$8

Sheet Parms
A1: Legends Inc. | G1: {=_xlfn.SEQUENCE(1,8,2022,1)} -> 2022 | H1: 2023 | I1: 2024 | J1: 2025 | K1: 2026 | L1: 2027 | M1: 2028 | N1: 2029
B2: Revenues
C3: Foot Solutions | G3: 8399 | H3: 8791 | I3: 8433 | J3: =+I3*(1+J7) -> 8719.722 | K3: =+J3*(1+K7) -> 9016.1925 | L3: =+K3*(1+L7) -> 9322.7431 | M3: =+L3*(1+M7) -> 9639.7164 | N3: =+M3*(1+N7) -> 9967.4667
C4: Greeting Fulfillments | G4: 8696 | H4: 8327 | I4: 8537 | J4: =+I4*(1+J8) -> 8852.869 | K4: =+J4*(1+K8) -> 9180.4252 | L4: =+K4*(1+L8) -> 9520.1009 | M4: =+L4*(1+M8) -> 9872.3446 | N4: =+M4*(1+N8) -> 10237.621
C5: Legendwear | G5: 8366 | H5: 8657 | I5: 8501 | J5: =+I5*(1+J9) -> 8832.539 | K5: =+J5*(1+K9) -> 9177.008 | L5: =+K5*(1+L9) -> 9534.9113 | M5: =+L5*(1+M9) -> 9906.7729 | N5: =+M5*(1+N9) -> 10293.137
B6: % Change
C7: {=+C3:C5} -> Foot Solutions | H7: 0.046672223 | I7: -0.040723467 | J7: 0.034 | K7: =+J7 -> 0.034 | L7: =AVERAGE(J7:K7) -> 0.034 | M7: =AVERAGE(K7:L7) -> 0.034 | N7: =AVERAGE(L7:M7) -> 0.034
C8: Greeting Fulfillments | H8: -0.042433303 | I8: 0.025219167 | J8: 0.037 | K8: =+J8 -> 0.037 | L8: =AVERAGE(J8:K8) -> 0.037 | M8: =AVERAGE(K8:L8) -> 0.037 | N8: =AVERAGE(L8:M8) -> 0.037
C9: Legendwear | H9: 0.034783648 | I9: -0.018020099 | J9: 0.039 | K9: =+J9 -> 0.039 | L9: =AVERAGE(J9:K9) -> 0.039 | M9: =AVERAGE(K9:L9) -> 0.039 | N9: =AVERAGE(L9:M9) -> 0.039
B10: Cost of Goods Sold
C11: {=+C3:C5} -> Foot Solutions | G11: 0.52854836 | H11: 0.51945532 | I11: 0.52962561 | J11: =AVERAGE(G11:I11) -> 0.52587643 | K11: =AVERAGE(H11:J11) -> 0.52498579 | L11: =AVERAGE(I11:K11) -> 0.52682928 | M11: =AVERAGE(J11:L11) -> 0.52589717 | N11: =AVERAGE(K11:M11) -> 0.52590408
C12: Greeting Fulfillments | G12: 0.54951212 | H12: 0.50621255 | I12: 0.54249378 | J12: =AVERAGE(G12:I12) -> 0.53273948 | K12: =AVERAGE(H12:J12) -> 0.5271486 | L12: =AVERAGE(I12:K12) -> 0.53412729 | M12: =AVERAGE(J12:L12) -> 0.53133846 | N12: =AVERAGE(K12:M12) -> 0.53087145
C13: Legendwear | G13: 0.50169648 | H13: 0.51854696 | I13: 0.53504035 | J13: =AVERAGE(G13:I13) -> 0.51842793 | K13: =AVERAGE(H13:J13) -> 0.52400508 | L13: =AVERAGE(I13:K13) -> 0.52582446 | M13: =AVERAGE(J13:L13) -> 0.52275249 | N13: =AVERAGE(K13:M13) -> 0.52419401
B14: Operating Expenses (aka fixed costs)
C15: Rent | G15: 0.04520141 | H15: 0.041519682 | I15: 0.041485585 | J15: 0.041 | K15: =AVERAGE(H15:J15) -> 0.041335089 | L15: =AVERAGE(I15:K15) -> 0.041273558 | M15: =AVERAGE(J15:L15) -> 0.041202882 | N15: =AVERAGE(K15:M15) -> 0.04127051
C16: Utilities | G16: 0.039664353 | H16: 0.04825251 | I16: 0.0428629 | J16: 0.043 | K16: =AVERAGE(H16:J16) -> 0.044705137 | L16: =AVERAGE(I16:K16) -> 0.043522679 | M16: =AVERAGE(J16:L16) -> 0.043742605 | N16: =AVERAGE(K16:M16) -> 0.04399014
C17: Phone | G17: 0.030733282 | H17: 0.037306794 | I17: 0.041556613 | J17: =AVERAGE(G17:I17) -> 0.03653223 | K17: =AVERAGE(H17:J17) -> 0.038465212 | L17: =AVERAGE(I17:K17) -> 0.038851352 | M17: =AVERAGE(J17:L17) -> 0.037949598 | N17: =AVERAGE(K17:M17) -> 0.038422054
C18: Advertising | G18: 0.031545546 | H18: 0.037579353 | I18: 0.036485053 | J18: =AVERAGE(G18:I18) -> 0.035203317 | K18: =AVERAGE(H18:J18) -> 0.036422575 | L18: =AVERAGE(I18:K18) -> 0.036036982 | M18: =AVERAGE(J18:L18) -> 0.035887625 | N18: =AVERAGE(K18:M18) -> 0.036115727
C19: Salaries | G19: 0.037692894 | H19: 0.046375124 | I19: 0.033670329 | J19: 0.036 | K19: =+J19 -> 0.036 | L19: =AVERAGE(I19:K19) -> 0.035223443 | M19: =AVERAGE(J19:L19) -> 0.035741148 | N19: =AVERAGE(K19:M19) -> 0.035654864
C20: Depreciation Expense | G20: 1000 | H20: =+G20 -> 1000 | I20: =+H20 -> 1000 | J20: =+I20 -> 1000 | K20: =+J20 -> 1000 | L20: =+K20 -> 1000 | M20: =+L20 -> 1000 | N20: =+M20 -> 1000
C21: Amortization Expense | G21: 250 | H21: =+G21 -> 250 | I21: =+H21 -> 250 | J21: =+I21+LBO.Goodwill/20 -> 2841.0598 | K21: =+J21 -> 2841.0598 | L21: =+K21 -> 2841.0598 | M21: =+L21 -> 2841.0598 | N21: =+M21 -> 2841.0598
B22: Tax Rate | G22: 0.21
B23: Cash Dividends | G23: 1500 | H23: =+G23 -> 1500 | I23: =+H23 -> 1500 | J23: 0 | K23: =+J23 -> 0 | L23: =+K23 -> 0 | M23: =+L23 -> 0 | N23: =+M23 -> 0
B24: Stock Buybacks | G24: 500 | H24: =+G24 -> 500 | I24: =+H24 -> 500 | J24: 0 | K24: =+J24 -> 0 | L24: =+K24 -> 0 | M24: =+L24 -> 0 | N24: =+M24 -> 0
B25: Balance Sheet
C26: Working Capital
D27: Accounts Receivable (days of Sales) | G27: 60 | H27: =+G27 -> 60 | I27: =+H27 -> 60 | J27: 55 | K27: 50 | L27: 45 | M27: 43 | N27: =+M27 -> 43
D28: Inventory (days of COGS) | G28: 32 | H28: =+G28 -> 32 | I28: =+H28 -> 32 | J28: 28 | K28: 26 | L28: 24 | M28: 23 | N28: =+M28 -> 23
D29: Prepaid Expenses | G29: 0.03 | H29: =+G29 -> 0.03 | I29: =+H29 -> 0.03 | J29: =+I29 -> 0.03 | K29: =+J29 -> 0.03 | L29: =+K29 -> 0.03 | M29: =+L29 -> 0.03 | N29: =+M29 -> 0.03
D30: Accounts Payable (days COGS) | G30: 35 | H30: =+G30 -> 35 | I30: =+H30 -> 35 | J30: 40 | K30: 45 | L30: =+K30 -> 45 | M30: 47 | N30: =+M30 -> 47
D31: Accrued Liabilities | G31: 0.03 | H31: =+G31 -> 0.03 | I31: =+H31 -> 0.03 | J31: =+I31 -> 0.03 | K31: =+J31 -> 0.03 | L31: =+K31 -> 0.03 | M31: =+L31 -> 0.03 | N31: =+M31 -> 0.03
C32: Capital Expenditure (CAPEX) | H32: 2500 | I32: =+H32 -> 2500 | J32: 1750 | K32: =+J32 -> 1750 | L32: =+K32 -> 1750 | M32: =+L32 -> 1750 | N32: =+M32 -> 1750
C33: Starting Gross PP&E | G33: 6000
C34: Starting Accumulated Depreciation | G34: 1500
C35: Starting.Goodwill | G35: 2000
C36: Starting Cash | G36: 4500

Sheet LBO Returns
A1: LBO Returns Calculation
B2: Weighted Average Cost of Capital (WACC) Post LBO
C3: Capital | G3: {=+dates.forecast} -> 2025 | H3: 2026 | I3: 2027 | J3: 2028 | K3: 2029
D4: Revolver | G4: {=D.F.Revolver} -> 18500 | H4: 16603.763 | I4: 14303.886 | J4: 11645.471 | K4: 8713.3719
D5: Subordinated Debt | G5: {=D.F.Sub.Debt} -> 20000 | H5: 20000 | I5: 20000 | J5: 20000 | K5: 20000
D6: Equity | G6: {=F.Equity} -> 30001.093 | H6: 30328.966 | I6: 30978.917 | J6: 32075.321 | K6: 33552.851
C7: Total Capital | G7: =SUM(G4:G6) -> 68501.093 | H7: =SUM(H4:H6) -> 66932.729 | I7: =SUM(I4:I6) -> 65282.803 | J7: =SUM(J4:J6) -> 63720.792 | K7: =SUM(K4:K6) -> 62266.222
C8: Weights
D9: {=+D4:D6} -> Revolver | G9: {=_xlfn.ANCHORARRAY(G4)/$G$7:$K$7} -> 0.27006869 | H9: 0.24806643 | I9: 0.21910649 | J9: 0.18275779 | K9: 0.13993738
D10: Subordinated Debt | G10: {=_xlfn.ANCHORARRAY(G5)/$G$7:$K$7} -> 0.29196615 | H10: 0.29880748 | I10: 0.3063594 | J10: 0.31386929 | K10: 0.32120143
D11: Equity | G11: {=_xlfn.ANCHORARRAY(G6)/$G$7:$K$7} -> 0.43796517 | H11: 0.45312609 | I11: 0.47453412 | J11: 0.50337291 | K11: 0.53886119
C12: After-Tax Costs Of Capital
D13: {=+_xlfn.ANCHORARRAY(D9)} -> Revolver | G13: {=D.Rate.Revolver*(1-tax.rate)} -> 0.05925 | H13: 0.05925 | I13: 0.05925 | J13: 0.05925 | K13: 0.05925
D14: Subordinated Debt | G14: {=D.Rate.Sub.Debt*(1-tax.rate)} -> 0.08295 | H14: 0.08295 | I14: 0.08295 | J14: 0.08295 | K14: 0.08295
D15: Equity | G15: 0.2617 | H15: =+G15 -> 0.2617 | I15: =+H15 -> 0.2617 | J15: =+I15 -> 0.2617 | K15: =+J15 -> 0.2617
C16: WACC | G16: =SUMPRODUCT(G9:G11,G13:G15) -> 0.15483565 | H16: =SUMPRODUCT(H9:H11,H13:H15) -> 0.15806711 | I16: =SUMPRODUCT(I9:I11,I13:I15) -> 0.16258015 | J16: =SUMPRODUCT(J9:J11,J13:J15) -> 0.16859655 | K16: =SUMPRODUCT(K9:K11,K13:K15) -> 0.17595492
C17: Discount Factors
D18: 1-Year Factors | G18: {=1/(1+G16:K16)} -> 0.86592408 | H18: 0.86350781 | I18: 0.86015575 | J18: 0.85572733 | K18: 0.85037273
D19: Multi-Year Discount | G19: =PRODUCT($G18:G18) -> 0.86592408 | H19: =PRODUCT($G18:H18) -> 0.74773221 | I19: =PRODUCT($G18:I18) -> 0.64316616 | J19: =PRODUCT($G18:J18) -> 0.55037486 | K19: =PRODUCT($G18:K18) -> 0.46802377
B21: Unlevered Free Cash Flow | G21: {=+dates.forecast} -> 2025 | H21: 2026 | I21: 2027 | J21: 2028 | K21: 2029
C22: EBITDA | G22: {=FCF.Values} -> 7461.5239 | H22: 7601.3719 | I22: 7836.5742 | J22: 8202.3227 | K22: 8464.8535
D23: Less: Depreciation and Amortization | G23: -3841.0598 | H23: -3841.0598 | I23: -3841.0598 | J23: -3841.0598 | K23: -3841.0598
C24: EBIT | G24: 3620.4641 | H24: 3760.3121 | I24: 3995.5144 | J24: 4361.2629 | K24: 4623.7937
D25: tax rate | G25: 0.21 | H25: 0.21 | I25: 0.21 | J25: 0.21 | K25: 0.21
C26: EBIAT (NOPAT - Net Op Profit After Tax) | G26: 2860.1666 | H26: 2970.6466 | I26: 3156.4563 | J26: 3445.3977 | K26: 3652.797
D27: Add back: Depr & Amort | G27: 3841.0598 | H27: 3841.0598 | I27: 3841.0598 | J27: 3841.0598 | K27: 3841.0598
D28: Working Capital Change | G28: 552.35495 | H28: 521.32054 | I28: 366.14857 | J28: 188.0239 | K28: -89.119715
C29: Unlevered Cash From Operations | G29: 7253.5814 | H29: 7333.0269 | I29: 7363.6647 | J29: 7474.4814 | K29: 7404.7371
D30: Less: CAPEX | G30: -1750 | H30: -1750 | I30: -1750 | J30: -1750 | K30: -1750
C31: Unlevered Free Cash Flow | G31: 5503.5814 | H31: 5583.0269 | I31: 5613.6647 | J31: 5724.4814 | K31: 5654.7371
B33: Valuation
C34: Discount Factors | G34: {=+G19:K19} -> 0.86592408 | H34: 0.74773221 | I34: 0.64316616 | J34: 0.55037486 | K34: 0.46802377
C35: Discounted Unlevered FCF From Operations | G35: {=+G31:K31*_xlfn.ANCHORARRAY(G34)} -> 4765.6837 | H35: 4174.6091 | I35: 3610.5192 | J35: 3150.6107 | K35: 2646.5514
B37: Equity Calculations
G38: Exit Multiplier | H38: Terminal Enterprise Value | I38: Plus: Terminal Cash | J38: Less: Terminal Debt | K38: Terminal Equity Value | L38: PV TEV
G39: {=_xlfn.SEQUENCE(4,1,8,2)} -> 8 | H39: {=+_xlfn.ANCHORARRAY(G39)*LBO.Terminal.EBITDA} -> 67718.828 | I39: =+LBO.Terminal.Cash -> 9364.1988 | J39: =-Terminal.Debt -> -28713.372 | K39: =SUM(H39:J39) -> 48369.655 | L39: {=+K39:K42*Terminal.Discount.Factor} -> 22638.148
G40: 10 | H40: 84648.535 | I40: =+I39 -> 9364.1988 | J40: =+J39 -> -28713.372 | K40: =SUM(H40:J40) -> 65299.362 | L40: 30561.654
G41: 12 | H41: 101578.24 | I41: =+I40 -> 9364.1988 | J41: =+J40 -> -28713.372 | K41: =SUM(H41:J41) -> 82229.069 | L41: 38485.159
G42: 14 | H42: 118507.95 | I42: =+I41 -> 9364.1988 | J42: =+J41 -> -28713.372 | K42: =SUM(H42:J42) -> 99158.776 | L42: 46408.664
B43: Gecko's Performance
C44: Gecko's Equity Investment @ LBO | G44: =LBO.Sponsor.Equity -> 34796.051 | H44: ="WACC= "&TEXT(LBO.Terminal.WACC,"0%"&"") -> WACC= 18%
G45: Exit Multiplier | H45: NPV | I45: IRR | O45: {=+G45:G49} -> Exit Multiplier | P45: {=_xlfn.SEQUENCE(1,6,0,1)} -> 0 | Q45: 1 | R45: 2 | S45: 3 | T45: 4 | U45: 5
G46: {=_xlfn.SEQUENCE(4,1,8,2)} -> 8 | H46: =NPV(LBO.Terminal.WACC,Q46:U46)-LBO.Sponsor.Equity -> 4390.3222 | I46: =IRR(P46:U46) -> 0.21208101 | O46: 8 | P46: =-LBO.Sponsor.Equity -> -34796.051 | Q46: =G$31 -> 5503.5814 | R46: =H$31 -> 5583.0269 | S46: =I$31 -> 5613.6647 | T46: =J$31 -> 5724.4814 | U46: =K$31+K39 -> 54024.392
G47: 10 | H47: =NPV(LBO.Terminal.WACC,Q47:U47)-LBO.Sponsor.Equity -> 11918.608 | I47: =IRR(P47:U47) -> 0.2645995 | O47: 10 | P47: =+P46 -> -34796.051 | Q47: =G$31 -> 5503.5814 | R47: =H$31 -> 5583.0269 | S47: =I$31 -> 5613.6647 | T47: =J$31 -> 5724.4814 | U47: =K$31+K40 -> 70954.099
G48: 12 | H48: =NPV(LBO.Terminal.WACC,Q48:U48)-LBO.Sponsor.Equity -> 19446.893 | I48: =IRR(P48:U48) -> 0.30887216 | O48: 12 | P48: =+P47 -> -34796.051 | Q48: =G$31 -> 5503.5814 | R48: =H$31 -> 5583.0269 | S48: =I$31 -> 5613.6647 | T48: =J$31 -> 5724.4814 | U48: =K$31+K41 -> 87883.806
G49: 14 | H49: =NPV(LBO.Terminal.WACC,Q49:U49)-LBO.Sponsor.Equity -> 26975.178 | I49: =IRR(P49:U49) -> 0.34736829 | O49: 14 | P49: =+P48 -> -34796.051 | Q49: =G$31 -> 5503.5814 | R49: =H$31 -> 5583.0269 | S49: =I$31 -> 5613.6647 | T49: =J$31 -> 5724.4814 | U49: =K$31+K42 -> 104813.51
B51: Enterprise Value Scenarios Over Time
G52: Exit Multiplier | H52: {=+dates.forecast} -> 2025 | I52: 2026 | J52: 2027 | K52: 2028 | L52: 2029
F53: Enterprise Value Exit Scenarios | G53: {=_xlfn.SEQUENCE(4,1,8,2)} -> 8 | H53: {=_xlfn.ANCHORARRAY(G53)*LBO.Forecast.EBITDA} -> 59692.191 | I53: 60810.975 | J53: 62692.593 | K53: 65618.582 | L53: 67718.828
G54: 10 | H54: 74615.239 | I54: 76013.719 | J54: 78365.742 | K54: 82023.227 | L54: 84648.535
G55: 12 | H55: 89538.287 | I55: 91216.463 | J55: 94038.89 | K55: 98427.873 | L55: 101578.24
G56: 14 | H56: 104461.33 | I56: 106419.21 | J56: 109712.04 | K56: 114832.52 | L56: 118507.95
F57: Adjustments:
F58: Less: Debt | H58: {=-D.F.Revolver-D.F.Sub.Debt} -> -38500 | I58: -36603.763 | J58: -34303.886 | K58: -31645.471 | L58: -28713.372
F59: Plus: Cash | H59: {=+F.Cash} -> 6248.4564 | I59: 7292.4736 | J59: 8099.7554 | K59: 8816.8284 | L59: 9364.1988
F60: Net Equity Value | G60: {=_xlfn.SEQUENCE(4,1,8,2)} -> 8 | H60: {=+_xlfn.ANCHORARRAY(H53)+_xlfn.ANCHORARRAY(H58)+_xlfn.ANCHORARRAY(H59)} -> 27440.648 | I60: 31499.686 | J60: 36488.463 | K60: 42789.939 | L60: 48369.655
G61: 10 | H61: 42363.695 | I61: 46702.43 | J61: 52161.611 | K61: 59194.584 | L61: 65299.362
G62: 12 | H62: 57286.743 | I62: 61905.173 | J62: 67834.76 | K62: 75599.23 | L62: 82229.069
G63: 14 | H63: 72209.791 | I63: 77107.917 | J63: 83507.908 | K63: 92003.875 | L63: 99158.776
H64: {=_xlfn.SEQUENCE(1,5,1,1)} -> 1 | I64: 2 | J64: 3 | K64: 4 | L64: 5
F65: Annualized Returns for Gecko | G65: {=_xlfn.SEQUENCE(4,1,8,2)} -> 8 | H65: {=(_xlfn.ANCHORARRAY(H60)/LBO.Sponsor.Equity)^(1/_xlfn.ANCHORARRAY(H64))-1} -> -0.21138615 | I65: -0.048545265 | J65: 0.015956713 | K65: 0.053059541 | L65: 0.068091862
G66: 10 | H66: 0.21748573 | I66: 0.15852326 | J66: 0.14447685 | K66: 0.14205759 | L66: 0.13416384
G67: 12 | H67: 0.64635761 | I67: 0.3338239 | J67: 0.24922532 | K67: 0.21407874 | L67: 0.18767901
G68: 14 | H68: 1.0752295 | I68: 0.48862226 | J68: 0.33885193 | K68: 0.2751728 | L68: 0.23299195
F70: Cash on Cash Returns | G70: {=_xlfn.SEQUENCE(4,1,8,2)} -> 8 | H70: {=+_xlfn.ANCHORARRAY(H60)/LBO.Sponsor.Equity} -> 0.78861385 | I70: 0.90526611 | J70: 1.0486381 | K70: 1.2297355 | L70: 1.3900904
G71: 10 | H71: 1.2174857 | I71: 1.3421761 | J71: 1.499067 | K71: 1.7011869 | L71: 1.8766314
G72: 12 | H72: 1.6463576 | I72: 1.7790862 | J72: 1.9494959 | K72: 2.1726382 | L72: 2.3631724
G73: 14 | H73: 2.0752295 | I73: 2.2159962 | J73: 2.3999249 | K73: 2.6440896 | L73: 2.8497135

Sheet Transaction Summary
A1: Transaction Summary
B2: Valuation | I2: Sources and Uses of Cash
C3: EBITDA | G3: =Final.EBIT+Final.Amortization.Expense+Final.Depreciation.Expense -> 6831.1633 | J3: Sources | N3: $ | O3: % | P3: xEBITDA | Q3: Fee% | R3: Fee$
C4: Multiple | G4: 9.5 | K4: Balance Sheet Cash | N4: =DCF.Cash -> 3808.152 | O4: =+N4/$N$8 -> 0.048447181 | P4: =N4/EBITDA.LBO -> 0.55746758
D5: Enterprise Value | G5: =+G3*G4 -> 64896.051 | K5: Revolver | N5: 20000 | O5: =+N5/$N$8 -> 0.25443932 | P5: =N5/EBITDA.LBO -> 2.927759 | Q5: 0.03 | R5: =Q5*N5 -> 600
C6: Capitalization | K6: Subordinated Debt | N6: 20000 | O6: =+N6/$N$8 -> 0.25443932 | P6: =N6/EBITDA.LBO -> 2.927759 | Q6: 0.04 | R6: =Q6*N6 -> 800
D7: Less | K7: Sponsor Equity (Gecko Fund) | N7: =40000-5493+0.050895+289 -> 34796.051 | O7: =+N7/$N$8 -> 0.44267418 | P7: =N7/EBITDA.LBO -> 5.0937226
E8: Debt | G8: =-DCF.Debt -> -5500 | J8: Total Sources | N8: =SUM(N4:N7) -> 78604.203 | R8: =SUM(R4:R7) -> 1400
E9: Preferred Stock | G9: =-DCF.Pref.Stock -> -1500
D10: Add | J10: Uses
E11: Cash | G11: =+DCF.Cash -> 3808.152 | K11: Minimum Cash Balance | N11: =minimum.cash.balance -> 5000
C12: Net Offer Value to Shareholders | G12: =SUM(G5:G11) -> 61704.203 | K12: Purchase of Equity | N12: =G12 -> 61704.203
D13: Offer Per Share | G13: =G12/shares.outstanding -> 108.17429 | K13: Retire Debt | N13: =+DCF.Debt -> 5500
K14: Retire Pref Stock | N14: =+DCF.Pref.Stock -> 1500
B15: Other Assumptions | K15: M&A Fee | N15: =+goldman.sachs.fee -> 3500
C16: Revolver EBITDA Borrowing Base Multiplier | G16: 6 | K16: Debt Placement Fee | N16: =+JPM.Fee -> 1400
C17: Revolver Availability @ Close | G17: =G16*G3 -> 40986.98 | J17: Total Uses | N17: =SUM(N11:N16) -> 78604.203
C18: Minimum Cash Balance | G18: 5000 | K18: Checksum | N18: =N8-N17 -> 2.4106703e-07
C19: Fee: Mergers and Acquisitions Fee | G19: 3500
B21: Goodwill Calculation
C22: Purchase of Equity | G22: =+G12 -> 61704.203
D23: Less: Book Value of Assets | G23: =-(DCF.Equity-DCF.Pref.Stock) -> -9883.007
C24: Goodwill | G24: =SUM(G22,G23) -> 51821.196

Sheet Financial Statements
A1: =company.name&" Financial Statements" -> Legends Inc. Financial Statements
B2: Income Statement | G2: {=dates.hist} -> 2022 | H2: 2023 | I2: 2024 | J2: LBO | K2: {=dates.forecast} -> 2025 | L2: 2026 | M2: 2027 | N2: 2028 | O2: 2029
C3: Revenues
D4: {=+Parms!C3:C5} -> Foot Solutions | G4: {=P.H.Revenues} -> 8399 | H4: 8791 | I4: 8433 | K4: {=P.F.Revenues} -> 8719.722 | L4: 9016.1925 | M4: 9322.7431 | N4: 9639.7164 | O4: 9967.4667
D5: Greeting Fulfillments | G5: 8696 | H5: 8327 | I5: 8537 | K5: 8852.869 | L5: 9180.4252 | M5: 9520.1009 | N5: 9872.3446 | O5: 10237.621
D6: Legendwear | G6: 8366 | H6: 8657 | I6: 8501 | K6: 8832.539 | L6: 9177.008 | M6: 9534.9113 | N6: 9906.7729 | O6: 10293.137
C7: Total Revenues | G7: =SUM(G4:G6) -> 25461 | H7: =SUM(H4:H6) -> 25775 | I7: =SUM(I4:I6) -> 25471 | K7: =SUM(K4:K6) -> 26405.13 | L7: =SUM(L4:L6) -> 27373.626 | M7: =SUM(M4:M6) -> 28377.755 | N7: =SUM(N4:N6) -> 29418.834 | O7: =SUM(O4:O6) -> 30498.225
C9: Cost of Goods Sold
D10: {=+_xlfn.ANCHORARRAY(D4)} -> Foot Solutions | G10: {=P.H.COGS*P.H.Revenues} -> 4439.2777 | H10: 4566.5317 | I10: 4466.3328 | K10: {=P.F.Revenues*P.F.COGS} -> 4585.4963 | L10: 4733.3729 | M10: 4911.494 | N10: 5069.4995 | O10: 5241.9314
D11: Greeting Fulfillments | G11: 4778.5574 | H11: 4215.2319 | I11: 4631.2694 | K11: 4716.2728 | L11: 4839.4483 | M11: 5084.9457 | N11: 5245.5564 | O11: 5434.8609
D12: Legendwear | G12: 4197.1927 | H12: 4489.061 | I12: 4548.3781 | K12: 4579.0349 | L12: 4808.7988 | M12: 5013.6896 | N12: 5178.7902 | O12: 5395.6008
C13: Total Cost of Goods Sold | G13: =SUM(G10:G12) -> 13415.028 | H13: =SUM(H10:H12) -> 13270.825 | I13: =SUM(I10:I12) -> 13645.98 | K13: =SUM(K10:K12) -> 13880.804 | L13: =SUM(L10:L12) -> 14381.62 | M13: =SUM(M10:M12) -> 15010.129 | N13: =SUM(N10:N12) -> 15493.846 | O13: =SUM(O10:O12) -> 16072.393
C15: Gross Margin | G15: {=H.Revenues-H.COGS} -> 12045.972 | H15: 12504.175 | I15: 11825.02 | K15: {=F.Revenues-F.COGS} -> 12524.326 | L15: 12992.006 | M15: 13367.626 | N15: 13924.988 | O15: 14425.832
D16: % Revenues | G16: {=H.Gross.Margin/H.Revenues} -> 0.47311465 | H16: 0.48512805 | I16: 0.46425424 | K16: {=F.Gross.Margin/F.Revenues} -> 0.47431412 | L16: 0.47461764 | M16: 0.47106002 | N16: 0.47333582 | O16: 0.47300563
C18: Selling, General and Administrative Expenses (SG&A)(aka Operating Expenses)
D19: Rent | G19: {=H.Revenues*P.H.Fixed.Costs} -> 1150.8731 | H19: 1070.1698 | I19: 1056.6793 | K19: {=F.Revenues*P.F.Fixed.Costs} -> 1082.6103 | L19: 1131.4913 | M19: 1171.2509 | N19: 1212.1408 | O19: 1258.6773
D20: Utilities | G20: 1009.8941 | H20: 1243.7085 | I20: 1091.7609 | K20: 1135.4206 | L20: 1223.7417 | M20: 1235.0759 | N20: 1286.8564 | O20: 1341.6212
D21: Phone | G21: 782.5001 | H21: 961.58261 | I21: 1058.4885 | K21: 964.63828 | L21: 1052.9323 | M21: 1102.5142 | N21: 1116.4329 | O21: 1171.8045
D22: Advertising | G22: 803.18113 | H22: 968.60783 | I22: 929.3108 | K22: 929.54817 | L22: 997.01793 | M22: 1022.6487 | N22: 1055.7721 | O22: 1101.4656
D23: Salaries | G23: 959.69878 | H23: 1195.3188 | I23: 857.61694 | K23: 950.58468 | L23: 985.45053 | M23: 999.56224 | N23: 1051.4629 | O23: 1087.4101
D24: Depreciation Expense | G24: {=P.H.Depreciation.Expense} -> 1000 | H24: 1000 | I24: 1000 | K24: {=P.F.Depreciation.Expense} -> 1000 | L24: 1000 | M24: 1000 | N24: 1000 | O24: 1000
D25: Amortization Expense | G25: {=P.H.Amortization.Expense} -> 250 | H25: 250 | I25: 250 | K25: {=P.F.Amortization.Expense} -> 2841.0598 | L25: 2841.0598 | M25: 2841.0598 | N25: 2841.0598 | O25: 2841.0598
C26: Total SG&A Expenses | G26: =SUM(G19:G25) -> 5956.1472 | H26: =SUM(H19:H25) -> 6689.3875 | I26: =SUM(I19:I25) -> 6243.8565 | K26: =SUM(K19:K25) -> 8903.8618 | L26: =SUM(L19:L25) -> 9231.6935 | M26: =SUM(M19:M25) -> 9372.1117 | N26: =SUM(N19:N25) -> 9563.7248 | O26: =SUM(O19:O25) -> 9802.0384
C28: Earnings Before Interest and Taxes (EBIT) | G28: {=H.Gross.Margin-H.Fixed.Costs} -> 6089.825 | H28: 5814.7879 | I28: 5581.1633 | K28: {=F.Gross.Margin-F.Fixed.Costs} -> 3620.4641 | L28: 3760.3121 | M28: 3995.5144 | N28: 4361.2629 | O28: 4623.7937
D29: % Revenues | G29: {=H.Operating.Income/H.Revenues} -> 0.23918248 | H29: 0.22559798 | I29: 0.21911834 | K29: {=F.EBIT/F.Revenues} -> 0.13711215 | L29: 0.1373699 | M29: 0.14079741 | N29: 0.14824731 | O29: 0.15160862
C31: Interest Expense | G31: {=D.H.Interest.Expense} -> 525.5 | H31: 509.375 | I31: 370.25 | K31: {=D.F.Interest.Expense} -> 3487.5 | L31: 3345.2822 | M31: 3172.7914 | N31: 2973.4103 | O31: 2753.5029
C33: Earnings Before Taxes (EBT) | G33: {=H.EBIT-G31:I31} -> 5564.325 | H33: 5305.4129 | I33: 5210.9133 | K33: {=+F.EBIT-D.F.Interest.Expense} -> 132.9641 | L33: 415.02989 | M33: 822.72294 | N33: 1387.8526 | O33: 1870.2908
C35: Income Tax Expense | G35: {=+_xlfn.ANCHORARRAY(G33)*tax.rate} -> 1168.5082 | H35: 1114.1367 | I35: 1094.2918 | K35: {=F.EBT*tax.rate} -> 27.922461 | L35: 87.156276 | M35: 172.77182 | N35: 291.44904 | O35: 392.76107
C37: Net Income | G37: {=+_xlfn.ANCHORARRAY(G33)-_xlfn.ANCHORARRAY(G35)} -> 4395.8167 | H37: 4191.2762 | I37: 4116.6215 | K37: {=+F.EBT-_xlfn.ANCHORARRAY(K35)} -> 105.04164 | L37: 327.87361 | M37: 649.95113 | N37: 1096.4035 | O37: 1477.5297
C39: Less: Cash Dividends | G39: {=-P.H.Dividends} -> -1500 | H39: -1500 | I39: -1500 | K39: {=-P.F.Dividends} -> 0 | L39: 0 | M39: 0 | N39: 0 | O39: 0
C40: Change in Retained Earnings | G40: {=+_xlfn.ANCHORARRAY(G37)+_xlfn.ANCHORARRAY(G39)} -> 2895.8167 | H40: 2691.2762 | I40: 2616.6215 | K40: {=F.Net.Income+_xlfn.ANCHORARRAY(K39)} -> 105.04164 | L40: 327.87361 | M40: 649.95113 | N40: 1096.4035 | O40: 1477.5297
B43: Balance Sheet | G43: {=dates.hist} -> 2022 | H43: 2023 | I43: 2024 | J43: LBO | K43: {=dates.forecast} -> 2025 | L43: 2026 | M43: 2027 | N43: 2028 | O43: 2029
C44: Assets
D45: Short Term Assets
E46: Cash | G46: {=H.Cash} -> 4500 | H46: 5138.4745 | I46: 3808.152 | J46: =minimum.cash.balance -> 5000 | K46: {=F.Cash} -> 6248.4564 | L46: 7292.4736 | M46: 8099.7554 | N46: 8816.8284 | O46: 9364.1988
E47: Accounts Receivable | G47: {=H.Revenues*(P.H.Accounts.Rec.Days/365)} -> 4185.3699 | H47: 4236.9863 | I47: 4187.0137 | J47: =+I47 -> 4187.0137 | K47: {=F.Revenues*(P.F.Accts.Rec.Days/365)} -> 3978.8552 | L47: 3749.8117 | M47: 3498.6274 | N47: 3465.7804 | O47: 3592.9416
E48: Inventory | G48: {=H.COGS*(P.H.Inventory.Days/365)} -> 1176.112 | H48: 1163.4696 | I48: 1196.3599 | J48: =+I48 -> 1196.3599 | K48: {=F.COGS*(P.F.Inventory.Days/365)} -> 1064.8288 | L48: 1024.4442 | M48: 986.9674 | N48: 976.32455 | O48: 1012.7809
E49: Prepaid Expenses | G49: {=P.H.Prepaids*H.Revenues} -> 763.83 | H49: 773.25 | I49: 764.13 | J49: =+I49 -> 764.13 | K49: {=P.F.Prepaids*F.Revenues} -> 792.1539 | L49: 821.20877 | M49: 851.33266 | N49: 882.56502 | O49: 914.94675
D50: Total Short Term Assets | G50: =SUM(G46:G49) -> 10625.312 | H50: =SUM(H46:H49) -> 11312.18 | I50: =SUM(I46:I49) -> 9955.6556 | J50: =SUM(J46:J49) -> 11147.504 | K50: =SUM(K46:K49) -> 12084.294 | L50: =SUM(L46:L49) -> 12887.938 | M50: =SUM(M46:M49) -> 13436.683 | N50: =SUM(N46:N49) -> 14141.498 | O50: =SUM(O46:O49) -> 14884.868
D52: Long Term Assets
E53: Gross Property, Plant & Equipment | G53: =Starting.PPE -> 6000 | H53: =+G53+Parms!H32 -> 8500 | I53: =+H53+Parms!I32 -> 11000 | J53: =+I53 -> 11000 | K53: =+I53+Parms!J32 -> 12750 | L53: =+K53+Parms!K32 -> 14500 | M53: =+L53+Parms!L32 -> 16250 | N53: =+M53+Parms!M32 -> 18000 | O53: =+N53+Parms!N32 -> 19750
E54: less: Accumulated Depreciation | G54: =-Starting.Acc.Dep -> -1500 | H54: =+G54-H24 -> -2500 | I54: =+H54-I24 -> -3500 | J54: =+I54 -> -3500 | K54: =+I54-K24 -> -4500 | L54: =+K54-L24 -> -5500 | M54: =+L54-M24 -> -6500 | N54: =+M54-N24 -> -7500 | O54: =+N54-O24 -> -8500
E55: Net PP&E | G55: =SUM(G53:G54) -> 4500 | H55: =SUM(H53:H54) -> 6000 | I55: =SUM(I53:I54) -> 7500 | J55: =+SUM(J53:J54) -> 7500 | K55: =SUM(K53:K54) -> 8250 | L55: =SUM(L53:L54) -> 9000 | M55: =SUM(M53:M54) -> 9750 | N55: =SUM(N53:N54) -> 10500 | O55: =SUM(O53:O54) -> 11250
E56: Goodwill | G56: =starting.goodwill -> 2000 | H56: =+G56-H25 -> 1750 | I56: =+H56-I25 -> 1500 | J56: =+I56+LBO.Goodwill -> 53321.196 | K56: =+J56-K25 -> 50480.136 | L56: =+K56-L25 -> 47639.076 | M56: =+L56-M25 -> 44798.017 | N56: =+M56-N25 -> 41956.957 | O56: =+N56-O25 -> 39115.897
E57: Intellectual Property (IP) | G57: 1000 | H57: =+G57 -> 1000 | I57: =+H57 -> 1000 | J57: =+I57 -> 1000 | K57: =+J57 -> 1000 | L57: =+K57 -> 1000 | M57: =+L57 -> 1000 | N57: =+M57 -> 1000 | O57: =+N57 -> 1000
D58: Total Long Term Assets | G58: =SUM(G55:G57) -> 7500 | H58: =SUM(H55:H57) -> 8750 | I58: =SUM(I55:I57) -> 10000 | J58: =SUM(J55:J57) -> 61821.196 | K58: =SUM(K55:K57) -> 59730.136 | L58: =SUM(L55:L57) -> 57639.076 | M58: =SUM(M55:M57) -> 55548.017 | N58: =SUM(N55:N57) -> 53456.957 | O58: =SUM(O55:O57) -> 51365.897
C60: Total Assets | G60: {=+G50:I50+G58:I58} -> 18125.312 | H60: 20062.18 | I60: 19955.656 | J60: =+SUM(J58,J50) -> 72968.7 | K60: {=+K50:O50+K58:O58} -> 71814.43 | L60: 70527.015 | M60: 68984.699 | N60: 67598.455 | O60: 66250.765
C62: Capital (Liabilities and Shareholder Equity)
D63: Liabilities
E64: Short Term Liabilities
E65: Accounts Payable | G65: {=H.COGS*(P.H.Accounts.Pay.Days/365)} -> 1286.3725 | H65: 1272.5448 | I65: 1308.5187 | J65: =+I65 -> 1308.5187 | K65: {=F.COGS*(P.F.Accts.Pay.Days/365)} -> 1521.184 | L65: 1773.0764 | M65: 1850.5639 | N65: 1995.098 | O65: 2069.5958
E66: Accrued Liabilities | G66: {=H.Revenues*P.H.Accrued.Liabs} -> 763.83 | H66: 773.25 | I66: 764.13 | J66: =+I66 -> 764.13 | K66: {=F.Revenues*P.F.Accrued.Liabs} -> 792.1539 | L66: 821.20877 | M66: 851.33266 | N66: 882.56502 | O66: 914.94675
E67: Short Term Portion of LT Debt | G67: {=D.H.STDebt} -> 250 | H67: 2250 | I67: 1500 | J67: =+LBO.STDebt -> 1500 | K67: {=D.F.STDebt} -> 1896.2368 | L67: 2299.8777 | M67: 2658.4142 | N67: 2932.0994 | O67: 1500
E68: Total Short Term Liabilities | G68: =SUM(G65:G67) -> 2300.2025 | H68: =SUM(H65:H67) -> 4295.7948 | I68: =SUM(I65:I67) -> 3572.6487 | J68: =+SUM(J65:J67) -> 3572.6487 | K68: =SUM(K65:K67) -> 4209.5747 | L68: =SUM(L65:L67) -> 4894.1629 | M68: =SUM(M65:M67) -> 5360.3107 | N68: =SUM(N65:N67) -> 5809.7624 | O68: =SUM(O65:O67) -> 4484.5426
E70: Long Term Liabilities
E71: Long Term Debt | G71: {=D.H.LTDebt} -> 7750 | H71: 5500 | I71: 4000 | J71: =+LBO.LTDebt -> 38500 | K71: {=D.F.LTDebt} -> 36603.763 | L71: 34303.886 | M71: 31645.471 | N71: 28713.372 | O71: 27213.372
E72: Capitalized Leases | G72: 1000 | H72: =+G72 -> 1000 | I72: =+H72 -> 1000 | J72: =+I72 -> 1000 | K72: =+J72 -> 1000 | L72: =+K72 -> 1000 | M72: =+L72 -> 1000 | N72: =+M72 -> 1000 | O72: =+N72 -> 1000
E73: Total Long Term Liabilities | G73: =SUM(G71:G72) -> 8750 | H73: =SUM(H71:H72) -> 6500 | I73: =SUM(I71:I72) -> 5000 | J73: =SUM(J71:J72) -> 39500 | K73: =SUM(K71:K72) -> 37603.763 | L73: =SUM(L71:L72) -> 35303.886 | M73: =SUM(M71:M72) -> 32645.471 | N73: =SUM(N71:N72) -> 29713.372 | O73: =SUM(O71:O72) -> 28213.372
D75: Total Liabililities | G75: {=+G68:I68+G73:I73} -> 11050.203 | H75: 10795.795 | I75: 8572.6487 | J75: =+J68+J73 -> 43072.649 | K75: {=+K68:O68+K73:O73} -> 41813.338 | L75: 40198.048 | M75: 38005.782 | N75: 35523.134 | O75: 32697.914
D77: Shareholder Equity
E78: Preferred Stock | G78: 1500 | H78: =+G78 -> 1500 | I78: =+H78 -> 1500 | J78: 0 | K78: =+J78 -> 0 | L78: =+K78 -> 0 | M78: =+L78 -> 0 | N78: =+M78 -> 0 | O78: =+N78 -> 0
E79: Common Stock | G79: 3500 | H79: =+G79 -> 3500 | I79: =+H79 -> 3500 | J79: =+LBO.Sponsor.Equity -> 34796.051 | K79: =+J79 -> 34796.051 | L79: =+K79 -> 34796.051 | M79: =+L79 -> 34796.051 | N79: =+M79 -> 34796.051 | O79: =+N79 -> 34796.051
E80: Treasury Stock | G80: =-Parms!G24 -> -500 | H80: =+G80-Parms!H24 -> -1000 | I80: =+H80-Parms!I24 -> -1500 | J80: 0 | K80: =+J80 -> 0 | L80: =+K80-Parms!K24 -> 0 | M80: =+L80-Parms!L24 -> 0 | N80: =+M80-Parms!M24 -> 0 | O80: =+N80-Parms!N24 -> 0
E81: Retained Earnings | G81: =+G40+197.436-518.143-0.0003888 -> 2575.1094 | H81: =+G81+H40 -> 5266.3855 | I81: =+H81+I40 -> 7883.007 | J81: =0-JPM.Fee-goldman.sachs.fee -> -4900 | K81: =+J81+K40 -> -4794.9584 | L81: =+K81+L40 -> -4467.0848 | M81: =+L81+M40 -> -3817.1336 | N81: =+M81+N40 -> -2720.7301 | O81: =+N81+O40 -> -1243.2003
D82: Total Shareholders Equity | G82: =SUM(G78:G81) -> 7075.1094 | H82: =SUM(H78:H81) -> 9266.3855 | I82: =SUM(I78:I81) -> 11383.007 | J82: =SUM(J78:J81) -> 29896.051 | K82: =SUM(K78:K81) -> 30001.093 | L82: =SUM(L78:L81) -> 30328.966 | M82: =SUM(M78:M81) -> 30978.917 | N82: =SUM(N78:N81) -> 32075.321 | O82: =SUM(O78:O81) -> 33552.851
D84: Total Liabilities & Equity | G84: {=+_xlfn.ANCHORARRAY(G75)+G82:I82} -> 18125.312 | H84: 20062.18 | I84: 19955.656 | J84: =J75+J82 -> 72968.7 | K84: {=+_xlfn.ANCHORARRAY(K75)+K82:O82} -> 71814.43 | L84: 70527.015 | M84: 68984.699 | N84: 67598.455 | O84: 66250.765
E86: Checksum | G86: {=H.Total.Assets-H.Capital} -> 4.7439244e-09 | H86: 4.7512003e-09 | I86: 4.7512003e-09 | J86: =J60-J84 -> -2.3630855e-07 | K86: {=F.Total.Assets-F.Capital} -> -2.363231e-07 | L86: -2.363231e-07 | M86: -2.363231e-07 | N86: -2.363231e-07 | O86: -2.363231e-07
C89: Statement of Changes in Cash | G89: {=dates.hist} -> 2022 | H89: 2023 | I89: 2024 | K89: {=dates.forecast} -> 2025 | L89: 2026 | M89: 2027 | N89: 2028 | O89: 2029
D90: Cash from Operations
E91: Net Income | G91: {=H.Net.Income} -> 4395.8167 | H91: 4191.2762 | I91: 4116.6215 | K91: {=F.Net.Income} -> 105.04164 | L91: 327.87361 | M91: 649.95113 | N91: 1096.4035 | O91: 1477.5297
E92: Add Back Non Cash Items
F93: Depreciation Expense | G93: {=P.H.Depreciation.Expense} -> 1000 | H93: 1000 | I93: 1000 | K93: {=P.F.Depreciation.Expense} -> 1000 | L93: 1000 | M93: 1000 | N93: 1000 | O93: 1000
F94: Amortization Expense | G94: {=P.H.Amortization.Expense} -> 250 | H94: 250 | I94: 250 | K94: {=P.F.Amortization.Expense} -> 2841.0598 | L94: 2841.0598 | M94: 2841.0598 | N94: 2841.0598 | O94: 2841.0598
E95: Change in Working Capital
F96: {=E47:E49} -> Accounts Receivable | H96: {=+G47:G49-H47:H49} -> -51.616438 | I96: {=+H47:H49-I47:I49} -> 49.972603 | K96: {=+I47:I49-K47:K49} -> 208.15849 | L96: {=+K47:K49-L47:L49} -> 229.04346 | M96: {=+L47:L49-M47:M49} -> 251.18438 | N96: {=+M47:M49-N47:N49} -> 32.846941 | O96: {=+N47:N49-O47:O49} -> -127.16116
F97: Inventory | H97: 12.642471 | I97: -32.890357 | K97: 131.53111 | L97: 40.384634 | M97: 37.476768 | N97: 10.642856 | O97: -36.456385
F98: Prepaid Expenses | H98: -9.42 | I98: 9.12 | K98: -28.0239 | L98: -29.054872 | M98: -30.123888 | N98: -31.232356 | O98: -32.381737
F99: {=+E65:E66} -> Accounts Payable | H99: {=+H65:H66-G65:G66} -> -13.827702 | I99: {=+I65:I66-H65:H66} -> 35.973828 | K99: {=+K65:K66-I65:I66} -> 212.66535 | L99: {=+L65:L66-K65:K66} -> 251.89244 | M99: {=+M65:M66-L65:L66} -> 77.487431 | N99: {=+N65:N66-M65:M66} -> 144.53411 | O99: {=+O65:O66-N65:N66} -> 74.497831
F100: Accrued Liabilities | H100: 9.42 | I100: -9.12 | K100: 28.0239 | L100: 29.054872 | M100: 30.123888 | N100: 31.232356 | O100: 32.381737
D101: Total Cash from Operations | H101: =SUM(H91:H100) -> 5388.4745 | I101: =SUM(I91:I100) -> 5419.6775 | K101: =SUM(K91:K100) -> 4498.4564 | L101: =SUM(L91:L100) -> 4690.2539 | M101: =SUM(M91:M100) -> 4857.1595 | N101: =SUM(N91:N100) -> 5125.4872 | O101: =SUM(O91:O100) -> 5229.4698
D103: Cash from Investment
E104: CAPEX | G104: {=-P.H.CAPEX} -> 0 | H104: -2500 | I104: -2500 | K104: {=-P.F.CAPEX} -> -1750 | L104: -1750 | M104: -1750 | N104: -1750 | O104: -1750
E105: Loss/Gain on Disposal of Assets | G105: 0 | H105: =+G105 -> 0 | I105: =+H105 -> 0 | K105: =+I105 -> 0 | L105: =+K105 -> 0 | M105: =+L105 -> 0 | N105: =+M105 -> 0 | O105: =+N105 -> 0
D106: Total Cash from Investment | H106: =SUM(H104:H105) -> -2500 | I106: =SUM(I104:I105) -> -2500 | K106: =SUM(K104:K105) -> -1750 | L106: =SUM(L104:L105) -> -1750 | M106: =SUM(M104:M105) -> -1750 | N106: =SUM(N104:N105) -> -1750 | O106: =SUM(O104:O105) -> -1750
D108: Cash from Financing
E109: Borrowing/(repayment) of debt | H109: =+DebtSchedule!H9-DebtSchedule!G9 -> -250 | I109: =+DebtSchedule!I9-DebtSchedule!H9 -> -2250 | K109: =+DebtSchedule!K9-DebtSchedule!J9 -> -1500 | L109: =+DebtSchedule!L9-DebtSchedule!K9 -> -1896.2368 | M109: =+DebtSchedule!M9-DebtSchedule!L9 -> -2299.8777 | N109: =+DebtSchedule!N9-DebtSchedule!M9 -> -2658.4142 | O109: =+DebtSchedule!O9-DebtSchedule!N9 -> -2932.0994
E110: Issuance of Shares | H110: 0 | I110: 0 | K110: 0 | L110: 0 | M110: 0 | N110: 0 | O110: 0
E111: Cash Dividend | G111: {=-P.H.Dividends} -> -1500 | H111: -1500 | I111: -1500 | K111: {=-P.F.Dividends} -> 0 | L111: 0 | M111: 0 | N111: 0 | O111: 0
E112: Stock Buybacks | G112: {=-P.H.Buybacks} -> -500 | H112: -500 | I112: -500 | K112: {=-P.F.Buybacks} -> 0 | L112: 0 | M112: 0 | N112: 0 | O112: 0
D113: Total Cash From Financing | H113: =SUM(H109:H112) -> -2250 | I113: =SUM(I109:I112) -> -4250 | K113: =SUM(K109:K112) -> -1500 | L113: =SUM(L109:L112) -> -1896.2368 | M113: =SUM(M109:M112) -> -2299.8777 | N113: =SUM(N109:N112) -> -2658.4142 | O113: =SUM(O109:O112) -> -2932.0994
D115: Net Change in Cash | H115: {=H.Cash.Financing+H.Cash.From.Ops+H.Cash.Investment} -> 638.47448 | I115: -1330.3225 | K115: {=F.Cash.Financing+F.Cash.Investment+F.Cash.Ops} -> 1248.4564 | L115: 1044.0172 | M115: 807.28181 | N115: 717.07304 | O115: 547.3704
D116: Starting Cash Balance | H116: =+G117 -> 4500 | I116: =+H117 -> 5138.4745 | K116: =+J117 -> 5000 | L116: =+K117 -> 6248.4564 | M116: =+L117 -> 7292.4736 | N116: =+M117 -> 8099.7554 | O116: =+N117 -> 8816.8284
D117: Ending Cash Balance | G117: =starting.cash -> 4500 | H117: =+H116+H115 -> 5138.4745 | I117: =+I116+I115 -> 3808.152 | J117: =minimum.cash.balance -> 5000 | K117: =+K116+K115 -> 6248.4564 | L117: =+L116+L115 -> 7292.4736 | M117: =+M116+M115 -> 8099.7554 | N117: =+N116+N115 -> 8816.8284 | O117: =+O116+O115 -> 9364.1988

Sheet DCF Analysis
A1: ="Discount Cash Flow Model for "&company.name -> Discount Cash Flow Model for Legends Inc.
B2: General Assumptions
C3: Share Price @ Last Close | G3: {=+_FV(H3,"Price")} -> 10.375 | H3: #VALUE!
C4: Shares Outstanding (mm's) | G4: {=_FV(H3,"Shares outstanding",TRUE)/1000000} -> 570.4147
C5: Market Capitaliztion ($mm's) | G5: {=+_FV(H3,"Market cap",TRUE)/1000000} -> 5918.0525
B7: Weighted Averaged Cost of Capital (WACC) | G7: Amount | H7: Weight | I7: Cost
C8: Debt | G8: =DCF.Debt -> 5500 | H8: =+G8/$G$11 -> 0.32577135 | I8: =+(DCF.Interest.Expense/DCF.Debt)*(1-tax.rate) -> 0.053181364
C9: Preferred Stock | G9: =DCF.Pref.Stock -> 1500 | H9: =+G9/$G$11 -> 0.088846732 | I9: 0.0773
C10: Common Stock (aka Equity) | G10: =DCF.Equity-DCF.Pref.Stock -> 9883.007 | H10: =+G10/$G$11 -> 0.58538192 | I10: 0.1883
G11: =SUM(G8:G10) -> 16883.007
B12: WACC | G12: =SUMPRODUCT(H8:H10,I8:I10) -> 0.13442023
B14: Free Cash Flow Buildup | G14: {=dates.forecast} -> 2025 | H14: 2026 | I14: 2027 | J14: 2028 | K14: 2029
C15: EBITDA | G15: {=_xlfn.ANCHORARRAY(G17)-_xlfn.ANCHORARRAY(G16)} -> 7461.5239 | H15: 7601.3719 | I15: 7836.5742 | J15: 8202.3227 | K15: 8464.8535
D16: Less: Depreciation and Amortization | G16: {=-P.F.Depreciation.Expense-P.F.Amortization.Expense} -> -3841.0598 | H16: -3841.0598 | I16: -3841.0598 | J16: -3841.0598 | K16: -3841.0598
C17: EBIT | G17: {=F.EBIT} -> 3620.4641 | H17: 3760.3121 | I17: 3995.5144 | J17: 4361.2629 | K17: 4623.7937
D18: tax rate | G18: =tax.rate -> 0.21 | H18: =tax.rate -> 0.21 | I18: =tax.rate -> 0.21 | J18: =tax.rate -> 0.21 | K18: =tax.rate -> 0.21
C19: EBIAT (NOPAT - Net Op Profit After Tax) | G19: {=_xlfn.ANCHORARRAY(G17)*(1-G18:K18)} -> 2860.1666 | H19: 2970.6466 | I19: 3156.4563 | J19: 3445.3977 | K19: 3652.797
D20: Add back: Depr & Amort | G20: {=-_xlfn.ANCHORARRAY(G16)} -> 3841.0598 | H20: 3841.0598 | I20: 3841.0598 | J20: 3841.0598 | K20: 3841.0598
D21: Working Capital Change | G21: =SUM('Financial Statements'!K96:K100) -> 552.35495 | H21: =SUM('Financial Statements'!L96:L100) -> 521.32054 | I21: =SUM('Financial Statements'!M96:M100) -> 366.14857 | J21: =SUM('Financial Statements'!N96:N100) -> 188.0239 | K21: =SUM('Financial Statements'!O96:O100) -> -89.119715
C22: Unlevered Cash From Operations | G22: =SUM(G19:G21) -> 7253.5814 | H22: =SUM(H19:H21) -> 7333.0269 | I22: =SUM(I19:I21) -> 7363.6647 | J22: =SUM(J19:J21) -> 7474.4814 | K22: =SUM(K19:K21) -> 7404.7371
D23: Less: CAPEX | G23: {=-P.F.CAPEX} -> -1750 | H23: -1750 | I23: -1750 | J23: -1750 | K23: -1750
C24: Unlevered Free Cash Flow | G24: {=+G22:K22+_xlfn.ANCHORARRAY(G23)} -> 5503.5814 | H24: 5583.0269 | I24: 5613.6647 | J24: 5724.4814 | K24: 5654.7371
D25: Discount Factor | G25: =1/(1+WACC)^G100 -> 0.88150755 | H25: =1/(1+WACC)^H100 -> 0.77705556 | I25: =1/(1+WACC)^I100 -> 0.68498034 | J25: =1/(1+WACC)^J100 -> 0.60381535 | K25: =1/(1+WACC)^K100 -> 0.53226779
C26: Discounted Free Cash Flow | G26: {=+_xlfn.ANCHORARRAY(G24)*G25:K25} -> 4851.4486 | H26: 4338.3221 | I26: 3845.25 | J26: 3456.5297 | K26: 3009.8344
C28: Net Present Value of the DCF | G28: =SUM(_xlfn.ANCHORARRAY(G26)) -> 19501.385
B30: Enterprise Valuations
C31: Perpetuity Approach
D32: Unlevered FCF Year 5 | G32: =DCF.Terminal.Free.Cash.Flow -> 5654.7371
D33: Long Term Growth Rate | G33: 0.04
D34: Forecast Year 6 FCF | G34: =+G32*(1+G33) -> 5880.9266
C35: Terminal Value | G35: =+G34/(WACC-G33) -> 62284.602
C36: NPV Calculation
D37: PV of the Terminal Value | G37: =+G35*DCF.Terminal.Discount.Factor -> 33152.087
D38: PV of the Free Cash Flows | G38: =+DCF.NPV.DCF -> 19501.385
C39: Total Enterprise Value | G39: =SUM(G37:G38) -> 52653.472
D40: Implied Term Value Exit Multiplier | G40: =G39/DCF.Terminal.EBITDA -> 6.2202461
C42: Exit EBITDA Multiple Approach
C43: Terminal Value Calculation
D44: EBITDA Year 5 | G44: =DCF.Terminal.EBITDA -> 8464.8535
D45: Expected Exit Multiplier | G45: 8
C46: Terminal Value Calculation | G46: =+G44*G45 -> 67718.828
C47: Enterprise Value Calculation
D48: PV of the Terminal Value | G48: =+G46*DCF.Terminal.Discount.Factor -> 36044.551
D49: PV of the Free Cash Flows | G49: =+DCF.NPV.DCF -> 19501.385
C50: Total Enterprise Value | G50: =SUM(G48:G49) -> 55545.935
D51: Implied Term Value Perpetual Growth Rate | G51: =+(WACC-DCF.Terminal.Free.Cash.Flow/G46)/(1-DCF.Terminal.Free.Cash.Flow/G46) -> 0.055556174
B53: Fair Value Per Share | G53: Approach
G54: Perpetuity | H54: Multiple
B55: Valuation
C56: Enterprise Value | G56: =TV.Gordon -> 52653.472 | H56: =TV.EBITDA.Mult -> 55545.935
D57: Less: Debt | G57: =-DCF.Debt -> -5500 | H57: =+G57 -> -5500
D58: Less: Pref Shares | G58: =-DCF.Pref.Stock -> -1500 | H58: =+G58 -> -1500
C59: Net Residual Value (aka Net Equity Value) | G59: =SUM(G56:G58) -> 45653.472 | H59: =SUM(H56:H58) -> 48545.935
C60: Diluted Shares | G60: =shares.outstanding -> 570.4147 | H60: =shares.outstanding -> 570.4147
B61: Equity Value Per Share | G61: =+G59/G60 -> 80.035581 | H61: =+H59/H60 -> 85.106389
C62: Market Premium (Discount) per Share | G62: =+G61/market.price-1 -> 6.7142729 | H62: =+H61/market.price-1 -> 7.2030255
B64: Golden Flash Hybrid Top-Down, Bottom-Up Valuation Model
C65: Weights Based on Reduced Form Integration | G65: 0.3871 | H65: =100%-G65 -> 0.6129
B66: GFHTDBUVM Value | G66: =SUMPRODUCT(G61:H61,G65:H65) -> 83.143479
H68: Equity Value Per Share
I69: Long-Term Growth Rate
H70: =+G61 -> 80.035581 | I70: {=_xlfn.SEQUENCE(1,5,2%,1%)} -> 0.02 | J70: 0.03 | K70: 0.04 | L70: 0.05 | M70: 0.06
G71: WACC | H71: {=_xlfn.SEQUENCE(5,1,11.5%,2%)} -> 0.115 | I71: 85.361598 | J71: 93.304509 | K71: 103.36553 | L71: 116.52225 | M71: 134.46323 | N71: Table.Perpetuity
H72: 0.135 | I72: 68.549529 | J72: 73.496634 | K72: 79.485235 | L72: 86.882918 | M72: 96.253317
H73: 0.155 | I73: 56.708063 | J73: 60.009097 | K73: 63.884224 | L73: 68.49747 | M73: 74.081926
H74: 0.175 | I74: 47.913975 | J74: 50.228013 | K74: 52.884872 | L74: 55.966828 | M74: 59.584777
H75: 0.195 | I75: 41.123143 | J75: 42.806701 | K75: 44.707493 | L75: 46.870462 | M75: 49.353871
H77: Equity Value Per Share | W77: 6787
I78: EBITDA Multiple
H79: =+H61 -> 85.106389 | I79: {=_xlfn.SEQUENCE(1,5,8,1)} -> 8 | J79: 9 | K79: 10 | L79: 11 | M79: 12
G80: WACC | H80: {=_xlfn.SEQUENCE(5,1,11.5%,2%)} -> 0.115 | I80: 92.487359 | J80: 101.09837 | K80: 109.70939 | L80: 118.32041 | M80: 126.93142 | N80: Table.Multiplier
H81: 0.135 | I81: 84.896891 | J81: 92.775498 | K81: 100.65411 | L81: 108.53271 | M81: 116.41132
H82: 0.155 | I82: 78.025633 | J82: 85.245328 | K82: 92.465022 | L82: 99.684716 | M82: 106.90441
H83: 0.175 | I83: 71.793165 | J83: 78.418982 | K83: 85.044798 | L83: 91.670615 | M83: 98.296431
H84: 0.195 | I84: 66.129297 | J84: 72.218903 | K84: 78.308509 | L84: 84.398115 | M84: 90.487722
H86: Equity Value Per Share
G87: EBITDA % of Forecast | I87: EBITDA Multiple
H88: =+H61 -> 85.106389 | I88: {=_xlfn.SEQUENCE(1,5,8,1)} -> 8 | J88: 9 | K88: 10 | L88: 11 | M88: 12
G89: {=_xlfn.SEQUENCE(5,1,70%,15%)} -> 0.7 | H89: =+G89*DCF.Terminal.EBITDA -> 5925.3974 | I89: 66.149365 | J89: 71.678497 | K89: 77.207629 | L89: 82.736761 | M89: 88.265893
G90: 0.85 | H90: =+G90*DCF.Terminal.EBITDA -> 7195.1255 | I90: 75.627877 | J90: 82.341823 | K90: 89.055769 | L90: 95.769715 | M90: 102.48366
G91: 1 | H91: =+G91*DCF.Terminal.EBITDA -> 8464.8535 | I91: 85.106389 | J91: 93.005149 | K91: 100.90391 | L91: 108.80267 | M91: 116.70143
G92: 1.15 | H92: =+G92*DCF.Terminal.EBITDA -> 9734.5815 | I92: 94.584901 | J92: 103.66848 | K92: 112.75205 | L92: 121.83562 | M92: 130.9192
G93: 1.3 | H93: =+G93*DCF.Terminal.EBITDA -> 11004.31 | I93: 104.06341 | J93: 114.3318 | K93: 124.60019 | L93: 134.86858 | M93: 145.13697
F96: Football Field Calculations | G96: Low | H96: Difference | I96: High
F97: DCF Value 8X - 12X Multiplier | G97: =MIN(table.multiplier) -> 66.129297 | H97: =+I97-G97 -> 60.802126 | I97: =MAX(table.multiplier) -> 126.93142
F98: DCF Value 2%-6% Growth Rate | G98: =MIN(table.perpetuity) -> 41.123143 | H98: =+I98-G98 -> 93.340088 | I98: =MAX(table.perpetuity) -> 134.46323
F99: 52 Week Market High/Low | G99: {=_FV(stock,"52 week low",TRUE)} -> 5.63 | H99: =+I99-G99 -> 11.07 | I99: {=_FV(stock,"52 week high",TRUE)} -> 16.7
F100: years | G100: {=_xlfn.SEQUENCE(1,5,1,1)} -> 1 | H100: 2 | I100: 3 | J100: 4 | K100: 5

Sheet DebtSchedule
A1: =company.name&" Debt Schedule" -> Legends Inc. Debt Schedule
G2: {=dates.hist} -> 2022 | H2: 2023 | I2: 2024 | J2: LBO | K2: {=+dates.forecast} -> 2025 | L2: 2026 | M2: 2027 | N2: 2028 | O2: 2029
B3: Debt
C4: Huntington | G4: 2000 | H4: 1750 | I4: 1500 | J4: 0 | K4: =+J4 -> 0 | L4: =+K4 -> 0 | M4: =+L4 -> 0 | N4: =+M4 -> 0 | O4: =+N4 -> 0 | P4: =+O4 -> 0
C5: PNC | G5: 2500 | H5: =+G5 -> 2500 | I5: =+H5 -> 2500 | J5: 0 | K5: =+J5 -> 0 | L5: =+K5 -> 0 | M5: =+L5 -> 0 | N5: =+M5 -> 0 | O5: =+N5 -> 0 | P5: =+O5 -> 0
C6: Keybank | G6: 3500 | H6: 3500 | I6: 1500 | J6: 0 | K6: =+J6 -> 0 | L6: =+K6 -> 0 | M6: =+L6 -> 0 | N6: =+M6 -> 0 | O6: =+N6 -> 0 | P6: =+O6 -> 0
C7: LBO Revolver | G7: 0 | H7: 0 | I7: 0 | J7: =+LBO.Revolver -> 20000 | K7: =+J7+K26+K27 -> 18500 | L7: =+K7+L26+L27 -> 16603.763 | M7: =+L7+M26+M27 -> 14303.886 | N7: =+M7+N26+N27 -> 11645.471 | O7: =+N7+O26+O27 -> 8713.3719 | P7: =+O7+P26+P27 -> 7213.3719
C8: Subordinated Debt | G8: 0 | H8: 0 | I8: 0 | J8: =+LBO.SubDebt -> 20000 | K8: =+J8 -> 20000 | L8: =+K8 -> 20000 | M8: =+L8 -> 20000 | N8: =+M8 -> 20000 | O8: =+N8 -> 20000 | P8: =+O8 -> 20000
B9: Total Debt | G9: =SUM(G4:G8) -> 8000 | H9: =SUM(H4:H8) -> 7750 | I9: =SUM(I4:I8) -> 5500 | J9: =SUM(J4:J8) -> 40000 | K9: =SUM(K4:K8) -> 38500 | L9: =SUM(L4:L8) -> 36603.763 | M9: =SUM(M4:M8) -> 34303.886 | N9: =SUM(N4:N8) -> 31645.471 | ... P9: =SUM(P4:P8) -> 27213.372
I10: DCF.Debt
B11: Interest Rate
C12: {=+C4:C8} -> Huntington | G12: 0.0645 | H12: =+G12 -> 0.0645 | I12: =+H12 -> 0.0645 | K12: =+I12 -> 0.0645 | L12: =+K12 -> 0.0645 | M12: =+L12 -> 0.0645 | N12: =+M12 -> 0.0645 | O12: =+N12 -> 0.0645
C13: PNC | G13: 0.0725 | H13: =+G13 -> 0.0725 | I13: =+H13 -> 0.0725 | K13: =+I13 -> 0.0725 | L13: =+K13 -> 0.0725 | M13: =+L13 -> 0.0725 | N13: =+M13 -> 0.0725 | O13: =+N13 -> 0.0725
C14: Keybank | G14: 0.0615 | H14: =+G14 -> 0.0615 | I14: =+H14 -> 0.0615 | K14: =+I14 -> 0.0615 | L14: =+K14 -> 0.0615 | M14: =+L14 -> 0.0615 | N14: =+M14 -> 0.0615 | O14: =+N14 -> 0.0615
C15: LBO Revolver | G15: 0 | H15: =+G15 -> 0 | I15: =+H15 -> 0 | K15: 0.075 | L15: =+K15 -> 0.075 | M15: =+L15 -> 0.075 | N15: =+M15 -> 0.075 | O15: =+N15 -> 0.075
C16: Subordinated Debt | G16: 0 | H16: =+G16 -> 0 | I16: =+H16 -> 0 | K16: 0.105 | L16: =+K16 -> 0.105 | M16: =+L16 -> 0.105 | N16: =+M16 -> 0.105 | O16: =+N16 -> 0.105
B18: Interest Expense | G18: =SUMPRODUCT(G4:G8,G12:G16) -> 525.5 | H18: =SUMPRODUCT(H4:H8,H12:H16) -> 509.375 | I18: =SUMPRODUCT(I4:I8,I12:I16) -> 370.25 | K18: =SUMPRODUCT(K4:K8,K12:K16) -> 3487.5 | L18: =SUMPRODUCT(L4:L8,L12:L16) -> 3345.2822 | M18: =SUMPRODUCT(M4:M8,M12:M16) -> 3172.7914 | N18: =SUMPRODUCT(N4:N8,N12:N16) -> 2973.4103 | O18: =SUMPRODUCT(O4:O8,O12:O16) -> 2753.5029
B20: Calculate Current Portion of Long Term Debt
C21: Current Portion | G21: =+G9-H9 -> 250 | H21: =+H9-I9 -> 2250 | I21: =+J9-K9 -> 1500 | J21: =+J9-K9 -> 1500 | K21: =+K9-L9 -> 1896.2368 | L21: =+L9-M9 -> 2299.8777 | M21: =+M9-N9 -> 2658.4142 | N21: =+N9-O9 -> 2932.0994 | O21: =+O9-P9 -> 1500
C22: Long Term Debt | G22: =+G9-G21 -> 7750 | H22: =+H9-H21 -> 5500 | I22: =+I9-I21 -> 4000 | J22: =+J9-J21 -> 38500 | K22: =+K9-K21 -> 36603.763 | L22: =+L9-L21 -> 34303.886 | M22: =+M9-M21 -> 31645.471 | N22: =+N9-N21 -> 28713.372 | O22: =+O9-O21 -> 27213.372
B24: Revolver Paydown
C25: Paydown Amounts
D26: Mandatory | K26: -1500 | L26: =+K26 -> -1500 | M26: =+L26 -> -1500 | N26: =+M26 -> -1500 | O26: =+N26 -> -1500 | P26: =+O26 -> -1500
D27: Variable | K27: {=+K44:O44} -> 0 | L27: -396.23678 | M27: -799.87768 | N27: -1158.4142 | O27: -1432.0994
C28: Revolver Discretionary Paydown Calculation
D29: Levered Free Cash Flow
E30: Net income | K30: {=+F.Net.Income} -> 105.04164 | L30: 327.87361 | M30: 649.95113 | N30: 1096.4035 | O30: 1477.5297
E31: Add Back:
F32: Depreciation | K32: {=P.F.Depreciation.Expense} -> 1000 | L32: 1000 | M32: 1000 | N32: 1000 | O32: 1000
F33: Amortization | K33: {=P.F.Amortization.Expense} -> 2841.0598 | L33: 2841.0598 | M33: 2841.0598 | N33: 2841.0598 | O33: 2841.0598
F34: Non-Cash Interest (aka: PIK) | K34: 0 | L34: =+K34 -> 0 | M34: =+L34 -> 0 | N34: =+M34 -> 0 | O34: =+N34 -> 0
E35: Change In Working Capital | K35: =+SUM('Financial Statements'!K96:K100) -> 552.35495 | L35: =+SUM('Financial Statements'!L96:L100) -> 521.32054 | M35: =+SUM('Financial Statements'!M96:M100) -> 366.14857 | N35: =+SUM('Financial Statements'!N96:N100) -> 188.0239 | O35: =+SUM('Financial Statements'!O96:O100) -> -89.119715
E36: CAPEX | K36: {=-P.F.CAPEX} -> -1750 | L36: -1750 | M36: -1750 | N36: -1750 | O36: -1750
D37: Net Levered Free Cash Flow | K37: =SUM(K26:K36) -> 1248.4564 | L37: =SUM(L26:L36) -> 1044.0172 | M37: =SUM(M26:M36) -> 807.28181 | N37: =SUM(N26:N36) -> 717.07304 | O37: =SUM(O26:O36) -> 547.3704
B38: Beginning Cash Balance | K38: {=F.STarting.Cash} -> 5000 | L38: 6248.4564 | M38: 7292.4736 | N38: 8099.7554 | O38: 8816.8284
C39: Less: Minimum Cash Balance | K39: =-minimum.cash.balance -> -5000 | L39: =-minimum.cash.balance -> -5000 | M39: =-minimum.cash.balance -> -5000 | N39: =-minimum.cash.balance -> -5000 | O39: =-minimum.cash.balance -> -5000
C40: Plus: Levered Free Cash Flow | K40: {=+K37:O37} -> 1248.4564 | L40: 1044.0172 | M40: 807.28181 | N40: 717.07304 | O40: 547.3704
D41: LFCF Before Scheduled Paydown | K41: =SUM(K38:K40) -> 1248.4564 | L41: =SUM(L38:L40) -> 2292.4736 | M41: =SUM(M38:M40) -> 3099.7554 | N41: =SUM(N38:N40) -> 3816.8284 | O41: =SUM(O38:O40) -> 4364.1988
E42: Less: Scheduled Revolver Paydown | K42: {=+K26:O26} -> -1500 | L42: -1500 | M42: -1500 | N42: -1500 | O42: -1500
D43: LFCF After Paydown | K43: =SUM(K41:K42) -> -251.54361 | L43: =SUM(L41:L42) -> 792.47356 | M43: =SUM(M41:M42) -> 1599.7554 | N43: =SUM(N41:N42) -> 2316.8284 | O43: =SUM(O41:O42) -> 2864.1988
E44: Less: Variable Paydown (% of LFCF) | J44: 0.5 | K44: =-MAX(0,K43*variable.paydown) -> 0 | L44: =-MAX(0,L43*variable.paydown) -> -396.23678 | M44: =-MAX(0,M43*variable.paydown) -> -799.87768 | N44: =-MAX(0,N43*variable.paydown) -> -1158.4142 | O44: =-MAX(0,O43*variable.paydown) -> -1432.0994
